xdbx/__init__.py
xdbx/config.py
xdbx/x_es.py
xdbx/x_kafka.py
xdbx/x_mysql.py
xdbx/x_postgres.py
xdbx/x_single.py
xdbx/x_sqlserver.py
xdbx-1.1.1.dist-info/LICENSE
xdbx-1.1.1.dist-info/METADATA
xdbx-1.1.1.dist-info/WHEEL
xdbx-1.1.1.dist-info/top_level.txt
xdbx-1.1.1.dist-info/RECORD
