Metadata-Version: 2.1
Name: xdbx
Version: 1.1.1
Home-page: https://gitee.com/spider-x/xdbx
Author: BruceLong
Author-email: 18656170559@163.com
License: MIT Licence
Platform: any
License-File: LICENSE
Requires-Dist: wheel
Requires-Dist: pymysql
Requires-Dist: psycopg2
Requires-Dist: pymssql (==2.2.4)
Requires-Dist: dbutils
Requires-Dist: pyxbox (>=0.0.3)
Requires-Dist: kafka-python
Requires-Dist: elasticsearch
Requires-Dist: pandas
Requires-Dist: xlsxwriter
